LICENSE
README.md
setup.py
pystoned2/CNLS.py
pystoned2/CNLSDDF.py
pystoned2/CNLSDDFG.py
pystoned2/CNLSG.py
pystoned2/CQER.py
pystoned2/CQERDDF.py
pystoned2/CQERG.py
pystoned2/CSVR.py
pystoned2/DEA.py
pystoned2/FDH.py
pystoned2/StoNED.py
pystoned2/__init__.py
pystoned2/constant.py
pystoned2/dataset.py
pystoned2/plot.py
pystoned2/weakCNLS.py
pystoned2/weakCNLSDDF.py
pystoned2/weakCNLSDDFG.py
pystoned2/weakCNLSG.py
pystoned2/weakCNLSb.py
pystoned2/weakCNLSbG.py
pystoned2/weakCNLSx.py
pystoned2/weakCNLSxG.py
pystoned2.egg-info/PKG-INFO
pystoned2.egg-info/SOURCES.txt
pystoned2.egg-info/dependency_links.txt
pystoned2.egg-info/not-zip-safe
pystoned2.egg-info/requires.txt
pystoned2.egg-info/top_level.txt
pystoned2/utils/CNLSDDFG1.py
pystoned2/utils/CNLSDDFG2.py
pystoned2/utils/CNLSDDFZG1.py
pystoned2/utils/CNLSDDFZG2.py
pystoned2/utils/CNLSG1.py
pystoned2/utils/CNLSG2.py
pystoned2/utils/CNLSZG1.py
pystoned2/utils/CNLSZG2.py
pystoned2/utils/CQERG1.py
pystoned2/utils/CQERG2.py
pystoned2/utils/CQERZG1.py
pystoned2/utils/CQERZG2.py
pystoned2/utils/__init__.py
pystoned2/utils/interpolation.py
pystoned2/utils/sweet.py
pystoned2/utils/tools.py
pystoned2/utils/weakCNLSDDFG1.py
pystoned2/utils/weakCNLSDDFG2.py
pystoned2/utils/weakCNLSDDFZG1.py
pystoned2/utils/weakCNLSDDFZG2.py
pystoned2/utils/weakCNLSG1.py
pystoned2/utils/weakCNLSG2.py
pystoned2/utils/weakCNLSZG1.py
pystoned2/utils/weakCNLSZG2.py
pystoned2/utils/weakCNLSbG1.py
pystoned2/utils/weakCNLSbG2.py
pystoned2/utils/weakCNLSbZG1.py
pystoned2/utils/weakCNLSbZG2.py
pystoned2/utils/weakCNLSxG1.py
pystoned2/utils/weakCNLSxG2.py
pystoned2/utils/weakCNLSxZG1.py
pystoned2/utils/weakCNLSxZG2.py
tests/__init__.py
tests/test_cnls.py
tests/test_weakCNLS.py