Metadata-Version: 2.1
Name: pystoned2
Version: 0.0.2
Summary: A Python Package for Convex Regression and Frontier Estimation
Home-page: https://github.com/advancehs/pyStoNED2
Author: Shuo Hu
Author-email: 1019753743@qq.com
License: GPLv3
Keywords: StoNED,CNLS,CER,CQR,Z-variables,CNLSG
Classifier: Development Status :: 5 - Production/Stable
Classifier: Intended Audience :: Science/Research
Classifier: Programming Language :: Python :: 3
Classifier: License :: OSI Approved :: GNU General Public License v3 (GPLv3)
Classifier: Operating System :: OS Independent
License-File: LICENSE
